odoo/addons/ssi_data_requirement_project/README.rst
odoo/addons/ssi_data_requirement_project/__init__.py
odoo/addons/ssi_data_requirement_project/__manifest__.py
odoo/addons/ssi_data_requirement_project/models/__init__.py
odoo/addons/ssi_data_requirement_project/models/data_requirement.py
odoo/addons/ssi_data_requirement_project/static/description/icon.png
odoo14_addon_ssi_data_requirement_project-14.0.1.0.0.dist-info/METADATA
odoo14_addon_ssi_data_requirement_project-14.0.1.0.0.dist-info/WHEEL
odoo14_addon_ssi_data_requirement_project-14.0.1.0.0.dist-info/top_level.txt
odoo14_addon_ssi_data_requirement_project-14.0.1.0.0.dist-info/RECORD
